strands_spot/__init__.py
strands_spot/use_spot.py
strands_spot-0.1.0.dist-info/licenses/LICENSE
strands_spot-0.1.0.dist-info/METADATA
strands_spot-0.1.0.dist-info/WHEEL
strands_spot-0.1.0.dist-info/top_level.txt
strands_spot-0.1.0.dist-info/RECORD
