Metadata-Version: 2.4
Name: strands-spot
Version: 0.1.0
Summary: Generic tool for Boston Dynamics Spot SDK for Strands Agents
Author-email: Cagatay Cali <cagataycali@icloud.com>
License: Apache-2.0
Project-URL: Homepage, https://github.com/cagataycali/strands-spot
Project-URL: Documentation, https://github.com/cagataycali/strands-spot/blob/main/README.md
Project-URL: Repository, https://github.com/cagataycali/strands-spot
Project-URL: Issues, https://github.com/cagataycali/strands-spot/issues
Keywords: spot,boston-dynamics,robotics,strands,agents,sdk
Classifier: Development Status :: 3 - Alpha
Classifier: Intended Audience :: Developers
Classifier: Topic :: Software Development :: Libraries :: Python Modules
Classifier: Topic :: Scientific/Engineering :: Artificial Intelligence
Classifier: License :: OSI Approved :: MIT License
Classifier: Programming Language :: Python :: 3
Classifier: Programming Language :: Python :: 3.8
Classifier: Programming Language :: Python :: 3.9
Classifier: Programming Language :: Python :: 3.10
Classifier: Programming Language :: Python :: 3.11
Classifier: Programming Language :: Python :: 3.12
Requires-Python: >=3.8
License-File: LICENSE
Requires-Dist: strands-agents
Requires-Dist: bosdyn-client>=5.0.0
Requires-Dist: bosdyn-api>=5.0.0
Requires-Dist: bosdyn-core>=5.0.0
Provides-Extra: dev
Requires-Dist: pytest>=7.0.0; extra == "dev"
Requires-Dist: pytest-cov>=4.0.0; extra == "dev"
Requires-Dist: black>=23.0.0; extra == "dev"
Requires-Dist: ruff>=0.1.0; extra == "dev"
Dynamic: license-file
